<?xml version = '1.0' encoding = 'UTF-8'?>
<Entity class="oracle.dbtools.crest.model.design.logical.Entity" directorySegmentName="seg_0" id="61F85EB6-9812-0637-611A-560484BAB3F7" name="SALES">
<createdBy>Henrique</createdBy>
<createdTime>2020-04-03 10:22:20 UTC</createdTime>
<commentInRDBMS><![CDATA[facts table, without a primary key; all rows are uniquely identified by the combination of all foreign keys]]></commentInRDBMS>
<generatorID>42FD93BA-AEE9-EED1-AB83-32F5FCCB786C</generatorID>
<ownerDesignName>dl_settings</ownerDesignName>
<engineerTo>
<item key="18AB2F7C-FC78-19CA-3443-3239FB643C29" value="true"/>
</engineerTo>
<adequatelyNormalized>NO</adequatelyNormalized>
<expectedVolumes>0</expectedVolumes>
<fwdEngineeringStrategyName>Single Table</fwdEngineeringStrategyName>
<growthPercent>0</growthPercent>
<growthType>Year</growthType>
<maxVolumes>9999999</maxVolumes>
<minVolumes>0</minVolumes>
<normalForm>Third</normalForm>
<attributes itemClass="oracle.dbtools.crest.model.design.logical.Attribute">
<Attribute name="CUST ID" id="0A07AA4E-237A-71BD-5457-C86CFA4D93E2">
<createdBy>Henrique</createdBy>
<createdTime>2020-04-03 10:22:20 UTC</createdTime>
<generatorID>B6477C74-0089-1596-3F4A-F4EB0018E313</generatorID>
<ownerDesignName>dl_settings</ownerDesignName>
<engineerTo>
<item key="18AB2F7C-FC78-19CA-3443-3239FB643C29" value="true"/>
</engineerTo>
<referedAttribute>3213585C-B941-BF2B-7913-C6706E8F21E7</referedAttribute>
<useDomainConstraints>false</useDomainConstraints>
<use>1</use>
<logicalDatatype>LOGDT019</logicalDatatype>
<ownDataTypeParameters>,,</ownDataTypeParameters>
</Attribute>
<Attribute name="CHANNEL ID" id="E369B7F0-BA94-A5CC-1113-0EFB5706B41C">
<createdBy>Henrique</createdBy>
<createdTime>2020-04-03 10:22:20 UTC</createdTime>
<generatorID>721C6B78-FBA5-3208-1658-E791E3F5FCBC</generatorID>
<ownerDesignName>dl_settings</ownerDesignName>
<engineerTo>
<item key="18AB2F7C-FC78-19CA-3443-3239FB643C29" value="true"/>
</engineerTo>
<nullsAllowed>true</nullsAllowed>
<referedAttribute>9C72760B-475C-8ADF-7146-B5E667E5EC71</referedAttribute>
<useDomainConstraints>false</useDomainConstraints>
<use>1</use>
<logicalDatatype>LOGDT025</logicalDatatype>
<dataTypeSize>1 BYTE</dataTypeSize>
<ownDataTypeParameters>,,</ownDataTypeParameters>
</Attribute>
<Attribute name="SALE DATE" id="2B5FC39A-4B48-450E-A4BD-5462F6614541">
<createdBy>Henrique</createdBy>
<createdTime>2020-04-03 10:22:20 UTC</createdTime>
<generatorID>374ECBEE-E656-516F-6C25-3A56CE584D8F</generatorID>
<ownerDesignName>dl_settings</ownerDesignName>
<engineerTo>
<item key="18AB2F7C-FC78-19CA-3443-3239FB643C29" value="true"/>
</engineerTo>
<nullsAllowed>true</nullsAllowed>
<useDomainConstraints>false</useDomainConstraints>
<use>1</use>
<logicalDatatype>LOGDT007</logicalDatatype>
<dataTypeSize>7</dataTypeSize>
<ownDataTypeParameters>7,,</ownDataTypeParameters>
</Attribute>
<Attribute name="EMPLOYEE ID" id="77110B26-FB9D-6749-7243-97E142F72829">
<createdBy>Henrique</createdBy>
<createdTime>2020-04-03 10:22:20 UTC</createdTime>
<generatorID>0477402E-AAFE-4340-B2B2-78B83CB56247</generatorID>
<ownerDesignName>dl_settings</ownerDesignName>
<engineerTo>
<item key="18AB2F7C-FC78-19CA-3443-3239FB643C29" value="true"/>
</engineerTo>
<nullsAllowed>true</nullsAllowed>
<referedAttribute>05CDC71C-0E9F-D15B-1EF3-F028ABED0133</referedAttribute>
<useDomainConstraints>false</useDomainConstraints>
<use>1</use>
<logicalDatatype>LOGDT019</logicalDatatype>
<dataTypePrecision>6</dataTypePrecision>
<dataTypeScale>0</dataTypeScale>
<ownDataTypeParameters>,,</ownDataTypeParameters>
</Attribute>
<Attribute name="SALE ID" id="56F6685A-F039-E8A7-9359-49418C15E557">
<createdBy>Henrique</createdBy>
<createdTime>2020-04-03 10:22:20 UTC</createdTime>
<commentInRDBMS><![CDATA[primary key]]></commentInRDBMS>
<generatorID>1BF182E1-CDAF-533F-7405-DBBE3A1C9CFF</generatorID>
<ownerDesignName>dl_settings</ownerDesignName>
<engineerTo>
<item key="18AB2F7C-FC78-19CA-3443-3239FB643C29" value="true"/>
</engineerTo>
<useDomainConstraints>false</useDomainConstraints>
<use>1</use>
<logicalDatatype>LOGDT019</logicalDatatype>
<ownDataTypeParameters>,,</ownDataTypeParameters>
</Attribute>
<Attribute name="STORE ID" id="B6BBF3EE-EF68-6F4C-291B-80318CA29913">
<createdBy>Henrique</createdBy>
<createdTime>2020-04-03 10:22:20 UTC</createdTime>
<generatorID>D2EF1696-E05B-221A-FB1C-13C16CFC5559</generatorID>
<ownerDesignName>dl_settings</ownerDesignName>
<engineerTo>
<item key="18AB2F7C-FC78-19CA-3443-3239FB643C29" value="true"/>
</engineerTo>
<nullsAllowed>true</nullsAllowed>
<useDomainConstraints>false</useDomainConstraints>
<use>1</use>
<logicalDatatype>LOGDT019</logicalDatatype>
<dataTypePrecision>6</dataTypePrecision>
<dataTypeScale>0</dataTypeScale>
<ownDataTypeParameters>,6,0</ownDataTypeParameters>
</Attribute>
<Attribute name="DONATION ID" id="C888A19F-03AF-A308-441A-200AA1041DBB">
<createdBy>Henrique</createdBy>
<createdTime>2020-04-03 10:22:20 UTC</createdTime>
<generatorID>0AD248B4-4114-1959-0B94-7C1EAF099401</generatorID>
<ownerDesignName>dl_settings</ownerDesignName>
<engineerTo>
<item key="18AB2F7C-FC78-19CA-3443-3239FB643C29" value="true"/>
</engineerTo>
<nullsAllowed>true</nullsAllowed>
<useDomainConstraints>false</useDomainConstraints>
<use>1</use>
<logicalDatatype>LOGDT019</logicalDatatype>
<dataTypePrecision>6</dataTypePrecision>
<dataTypeScale>0</dataTypeScale>
<ownDataTypeParameters>,6,0</ownDataTypeParameters>
</Attribute>
<Attribute name="ORDER ID" id="DE6D47AD-C6B8-0DA3-3C06-78677F598376">
<createdBy>Henrique</createdBy>
<createdTime>2020-04-03 10:22:20 UTC</createdTime>
<generatorID>64B25D68-E168-3AE1-6A98-64317F9960D4</generatorID>
<ownerDesignName>dl_settings</ownerDesignName>
<engineerTo>
<item key="18AB2F7C-FC78-19CA-3443-3239FB643C29" value="true"/>
</engineerTo>
<nullsAllowed>true</nullsAllowed>
<useDomainConstraints>false</useDomainConstraints>
<use>1</use>
<logicalDatatype>LOGDT019</logicalDatatype>
<dataTypePrecision>9</dataTypePrecision>
<dataTypeScale>0</dataTypeScale>
<ownDataTypeParameters>,9,0</ownDataTypeParameters>
</Attribute>
<Attribute name="DELIVERY ID" id="6FC423F8-EA52-6EC3-BD54-CF884BDA833E">
<createdBy>Henrique</createdBy>
<createdTime>2020-04-03 10:22:20 UTC</createdTime>
<generatorID>5927F20C-7B3C-9CC7-0885-E1FE1367541B</generatorID>
<ownerDesignName>dl_settings</ownerDesignName>
<engineerTo>
<item key="18AB2F7C-FC78-19CA-3443-3239FB643C29" value="true"/>
</engineerTo>
<nullsAllowed>true</nullsAllowed>
<useDomainConstraints>false</useDomainConstraints>
<use>1</use>
<logicalDatatype>LOGDT019</logicalDatatype>
<dataTypePrecision>6</dataTypePrecision>
<dataTypeScale>0</dataTypeScale>
<ownDataTypeParameters>,6,0</ownDataTypeParameters>
</Attribute>
<Attribute name="STORE PROMOTION ID" id="5FF98630-6B33-438D-FDA7-82E89D280BFB">
<createdBy>Henrique</createdBy>
<createdTime>2020-04-03 10:22:20 UTC</createdTime>
<generatorID>60E85762-43DB-616C-A777-61AD11A24B46</generatorID>
<ownerDesignName>dl_settings</ownerDesignName>
<engineerTo>
<item key="18AB2F7C-FC78-19CA-3443-3239FB643C29" value="true"/>
</engineerTo>
<nullsAllowed>true</nullsAllowed>
<useDomainConstraints>false</useDomainConstraints>
<use>1</use>
<logicalDatatype>LOGDT019</logicalDatatype>
<dataTypePrecision>6</dataTypePrecision>
<dataTypeScale>0</dataTypeScale>
<ownDataTypeParameters>,6,0</ownDataTypeParameters>
</Attribute>
<Attribute name="STATUS ID" id="7BEB6D18-9815-744D-0E2F-3CD876F97DAD">
<createdBy>Henrique</createdBy>
<createdTime>2020-04-03 10:22:20 UTC</createdTime>
<generatorID>36F24EB4-9E22-F257-35A5-7A827238BC61</generatorID>
<ownerDesignName>dl_settings</ownerDesignName>
<engineerTo>
<item key="18AB2F7C-FC78-19CA-3443-3239FB643C29" value="true"/>
</engineerTo>
<nullsAllowed>true</nullsAllowed>
<useDomainConstraints>false</useDomainConstraints>
<use>1</use>
<logicalDatatype>LOGDT019</logicalDatatype>
<dataTypePrecision>6</dataTypePrecision>
<dataTypeScale>0</dataTypeScale>
<ownDataTypeParameters>,6,0</ownDataTypeParameters>
</Attribute>
<Attribute name="CURRENCY ID" id="7C526E97-3BA2-E575-5F04-F3ADB4C2958A">
<createdBy>Henrique</createdBy>
<createdTime>2020-04-03 10:22:20 UTC</createdTime>
<generatorID>E2F7BF2D-2DFF-040F-807A-48088FBB904D</generatorID>
<ownerDesignName>dl_settings</ownerDesignName>
<engineerTo>
<item key="18AB2F7C-FC78-19CA-3443-3239FB643C29" value="true"/>
</engineerTo>
<nullsAllowed>true</nullsAllowed>
<useDomainConstraints>false</useDomainConstraints>
<use>1</use>
<logicalDatatype>LOGDT019</logicalDatatype>
<dataTypePrecision>9</dataTypePrecision>
<dataTypeScale>0</dataTypeScale>
<ownDataTypeParameters>,9,0</ownDataTypeParameters>
</Attribute>
<Attribute name="CURRENCY RATE" id="4DD868E9-76E7-42D7-06E0-03410C9AED8F">
<createdBy>Henrique</createdBy>
<createdTime>2020-04-03 10:22:20 UTC</createdTime>
<generatorID>790B687E-F860-4E2E-05E9-2C21B8CDC2EB</generatorID>
<ownerDesignName>dl_settings</ownerDesignName>
<engineerTo>
<item key="18AB2F7C-FC78-19CA-3443-3239FB643C29" value="true"/>
</engineerTo>
<nullsAllowed>true</nullsAllowed>
<useDomainConstraints>false</useDomainConstraints>
<use>1</use>
<logicalDatatype>LOGDT019</logicalDatatype>
<dataTypePrecision>9</dataTypePrecision>
<dataTypeScale>4</dataTypeScale>
<ownDataTypeParameters>,9,4</ownDataTypeParameters>
</Attribute>
<Attribute name="CREDIT COMPANY ID" id="EE2D3E23-4416-5119-AC06-F1DAE62A0CE7">
<createdBy>Henrique</createdBy>
<createdTime>2020-04-03 10:22:20 UTC</createdTime>
<generatorID>FEBFD556-01A7-ADC8-D2B7-1067120E7506</generatorID>
<ownerDesignName>dl_settings</ownerDesignName>
<engineerTo>
<item key="18AB2F7C-FC78-19CA-3443-3239FB643C29" value="true"/>
</engineerTo>
<nullsAllowed>true</nullsAllowed>
<useDomainConstraints>false</useDomainConstraints>
<use>1</use>
<logicalDatatype>LOGDT019</logicalDatatype>
<dataTypePrecision>9</dataTypePrecision>
<dataTypeScale>0</dataTypeScale>
<ownDataTypeParameters>,9,0</ownDataTypeParameters>
</Attribute>
<Attribute name="PAYMENT METHOD ID" id="52B21267-EE7B-3059-EEBB-5F9D94E2873A">
<createdBy>Henrique</createdBy>
<createdTime>2020-04-03 10:22:20 UTC</createdTime>
<generatorID>460DF3DA-E826-B246-B176-125FA7D2C656</generatorID>
<ownerDesignName>dl_settings</ownerDesignName>
<engineerTo>
<item key="18AB2F7C-FC78-19CA-3443-3239FB643C29" value="true"/>
</engineerTo>
<nullsAllowed>true</nullsAllowed>
<useDomainConstraints>false</useDomainConstraints>
<use>1</use>
<logicalDatatype>LOGDT019</logicalDatatype>
<dataTypePrecision>6</dataTypePrecision>
<dataTypeScale>0</dataTypeScale>
<ownDataTypeParameters>,6,0</ownDataTypeParameters>
</Attribute>
<Attribute name="CREDIT LIMIT ID" id="4921263A-E0C1-07B5-AF53-EEBDABD7CFDE">
<createdBy>Henrique</createdBy>
<createdTime>2020-04-03 10:22:20 UTC</createdTime>
<generatorID>CC7C6D3C-F43E-2DD6-38B2-1449A87C3474</generatorID>
<ownerDesignName>dl_settings</ownerDesignName>
<engineerTo>
<item key="18AB2F7C-FC78-19CA-3443-3239FB643C29" value="true"/>
</engineerTo>
<nullsAllowed>true</nullsAllowed>
<useDomainConstraints>false</useDomainConstraints>
<use>1</use>
<logicalDatatype>LOGDT019</logicalDatatype>
<dataTypePrecision>6</dataTypePrecision>
<dataTypeScale>0</dataTypeScale>
<ownDataTypeParameters>,6,0</ownDataTypeParameters>
</Attribute>
<Attribute name="WEATHER ID" id="833B5ECD-8BD1-1E73-9021-65F6B8F14E0E">
<createdBy>Henrique</createdBy>
<createdTime>2020-04-03 10:22:20 UTC</createdTime>
<generatorID>3E7AEB6F-E54D-3E22-67B1-CEED938AEE8F</generatorID>
<ownerDesignName>dl_settings</ownerDesignName>
<engineerTo>
<item key="18AB2F7C-FC78-19CA-3443-3239FB643C29" value="true"/>
</engineerTo>
<nullsAllowed>true</nullsAllowed>
<useDomainConstraints>false</useDomainConstraints>
<use>1</use>
<logicalDatatype>LOGDT019</logicalDatatype>
<dataTypePrecision>6</dataTypePrecision>
<dataTypeScale>0</dataTypeScale>
<ownDataTypeParameters>,6,0</ownDataTypeParameters>
</Attribute>
<Attribute name="MARKETING ID" id="98908296-5DDE-E366-F237-54852C50EC4E">
<createdBy>Henrique</createdBy>
<createdTime>2020-04-03 10:22:20 UTC</createdTime>
<generatorID>13E2C644-D5F7-FB58-2840-1D5F0BF2FCC7</generatorID>
<ownerDesignName>dl_settings</ownerDesignName>
<engineerTo>
<item key="18AB2F7C-FC78-19CA-3443-3239FB643C29" value="true"/>
</engineerTo>
<nullsAllowed>true</nullsAllowed>
<useDomainConstraints>false</useDomainConstraints>
<use>1</use>
<logicalDatatype>LOGDT019</logicalDatatype>
<dataTypePrecision>6</dataTypePrecision>
<dataTypeScale>0</dataTypeScale>
<ownDataTypeParameters>,6,0</ownDataTypeParameters>
</Attribute>
<Attribute name="DELIVERY COMPANY ID" id="6D27BEA8-2C67-F3C6-A31A-213B6F12FF77">
<createdBy>Henrique</createdBy>
<createdTime>2020-04-03 10:22:20 UTC</createdTime>
<generatorID>0297B75F-4EE6-0A9A-7666-73F3CD632696</generatorID>
<ownerDesignName>dl_settings</ownerDesignName>
<engineerTo>
<item key="18AB2F7C-FC78-19CA-3443-3239FB643C29" value="true"/>
</engineerTo>
<nullsAllowed>true</nullsAllowed>
<useDomainConstraints>false</useDomainConstraints>
<use>1</use>
<logicalDatatype>LOGDT019</logicalDatatype>
<dataTypePrecision>6</dataTypePrecision>
<dataTypeScale>0</dataTypeScale>
<ownDataTypeParameters>,6,0</ownDataTypeParameters>
</Attribute>
<Attribute name="SALESMAN FLEET ID" id="3E6CBD8F-536F-FDF3-B458-7804471B69AA">
<createdBy>Henrique</createdBy>
<createdTime>2020-04-03 10:22:20 UTC</createdTime>
<generatorID>D8E85DC6-F688-4807-D4C0-5B4F3C5FA070</generatorID>
<ownerDesignName>dl_settings</ownerDesignName>
<engineerTo>
<item key="18AB2F7C-FC78-19CA-3443-3239FB643C29" value="true"/>
</engineerTo>
<nullsAllowed>true</nullsAllowed>
<useDomainConstraints>false</useDomainConstraints>
<use>1</use>
<logicalDatatype>LOGDT019</logicalDatatype>
<dataTypePrecision>6</dataTypePrecision>
<dataTypeScale>0</dataTypeScale>
<ownDataTypeParameters>,6,0</ownDataTypeParameters>
</Attribute>
<Attribute name="CONTRIBUTION ID" id="3FF88854-1655-117B-9EE2-641F78F1C27D">
<createdBy>Henrique</createdBy>
<createdTime>2020-04-03 10:22:20 UTC</createdTime>
<generatorID>9B006824-72F9-EE69-3F70-4E1999738DBF</generatorID>
<ownerDesignName>dl_settings</ownerDesignName>
<engineerTo>
<item key="18AB2F7C-FC78-19CA-3443-3239FB643C29" value="true"/>
</engineerTo>
<nullsAllowed>true</nullsAllowed>
<useDomainConstraints>false</useDomainConstraints>
<use>1</use>
<logicalDatatype>LOGDT019</logicalDatatype>
<dataTypePrecision>6</dataTypePrecision>
<dataTypeScale>0</dataTypeScale>
<ownDataTypeParameters>,6,0</ownDataTypeParameters>
</Attribute>
<Attribute name="ID" id="8970D9DB-56E3-7660-9ED6-F25D94B7613F">
<createdBy>Henrique</createdBy>
<createdTime>2020-04-03 10:24:56 UTC</createdTime>
<generatorID>A50585A4-4B36-D2FB-74EB-574BDB5F0DE0</generatorID>
<ownerDesignName>dl_settings</ownerDesignName>
<engineerTo>
<item key="18AB2F7C-FC78-19CA-3443-3239FB643C29" value="true"/>
</engineerTo>
<referedAttribute>51617C42-44A9-F249-BCDE-C455AF7745BF</referedAttribute>
<useDomainConstraints>false</useDomainConstraints>
<use>1</use>
<logicalDatatype>LOGDT019</logicalDatatype>
<dataTypePrecision>15</dataTypePrecision>
<dataTypeScale>2</dataTypeScale>
<ownDataTypeParameters>,,</ownDataTypeParameters>
</Attribute>
</attributes>
<identifiers itemClass="oracle.dbtools.crest.model.design.logical.CandidateKey">
<identifier id="D6E735A9-2044-404B-B537-93BD7BF5F7FB" name="PK SALES">
<createdBy>Henrique</createdBy>
<createdTime>2020-04-03 10:22:20 UTC</createdTime>
<generatorID>39930B78-107D-B94E-F5E9-619353AEFAC3</generatorID>
<ownerDesignName>dl_settings</ownerDesignName>
<engineerTo>
<item key="18AB2F7C-FC78-19CA-3443-3239FB643C29" value="true"/>
</engineerTo>
<pk>true</pk>
<usedAttributes>
<attributeRef>56F6685A-F039-E8A7-9359-49418C15E557</attributeRef>
</usedAttributes>
</identifier>
</identifiers>
</Entity>